{
  "pdfPageNumber": 137,
  "surnameRange": [
    "Manger",
    "Marti"
  ],
  "textColumns": {
    "Spalte01": "Manger — 12\n\nManger-Flubacher Fr., Landjägerserg. u. Spez., 56 Müllerweg.\n— -Schneider Andreas, Lehenmann, 43 Schützenmattstr.\nMangold-Beh Heinr., Tagl., 111 Itelpfad.\n— -Fischer Wwe. Anna, Haushält., 26 Riehenthorstr.\n— -Greis Wilh., Wollenwaarendet., 2 Rümelinsplatz.\n— -Grieder Reinh., Holzhdl., 6 Petersg.\n— -Grillo Alex., Quartierschr., 15 Allschwylerstr.\n— -Joh. Jac., Postcommis, 35 Steinenvst.\n— -Kunz Wwe. Magd., Part., 26 Steinenbachgässl.\n— -Sam., Zimmerges., 26 Steinenbachgssl.\n— -Stänz Burkh., Secret. f. d. Niederlassungswesen, 4 Wallstr.\n— -Stiefvater Carl, Maurermstr., 29 Binningerstr.\n— -Tröndle Jacob, Landwirth, 80 Allschwylerstr.\n— -Tschan J. M. Fr., Färberges., 111 Itelpfad.\nMannock Ed., Commis, 40 Weberg.\nMantel J. Heinr., Agent, 2 Rheing.\nMantel & Bretscher, Leonhardsgr. 50. Commission u. Agentur in Colonialwaaren. E. Heinr. Mantel u. Otto Bretscher.\n— -Seiler Heinr., Gerberges., 2 Rümelinsplatz.\nManuel-Preiswerk A. C.Paul, Buchhalt., 33 Langeg.\nManz-Bucher Jac., Schuhmacherges., 7 Ochseneg.\n— -Erny Jb., Malerges., 23 U. Heunberg.\n— -Gloor Ed., Wirth., 16 Greifeng.\nMarbach-Amann Xav., Zimmerges., 138 Bläsiringweg.\n— -Bollier Hier., Schuhmachermstr., 23 Uteng.\n— -Flubacher Friedr., Bibliothekar, 8 Münsterplatz.\n— -Gysin Wwe. Anna, Part., 66 Missionsstr.\nMarbacher-Reig Ant., Wirth, 76 Johannvorst.\nMarbet-Mauch Aug., Posam., 6 Byfangw.\nMarchal-Botty Mich., Strohhutfabrikt, 20 Steinenvorst.",
    "Spalte02": "26 — Marti\n\nMarfort Elisab., Ladengehülfin, 8 Kohlenbergg.\n\n— -Hertner Wwe. Verena, Part., 8 Steinenthorstr.\n\n— -VonSpeyr Albert, Sattlermstr., 37 Freistr.\n\n— -VonSpeyr Ant., Kfm., 3 Claraplatz.\n\nAnt. Marfort, St. Elisabethenstrasse 11. Spedition, Commission u. Agen- turen. E. Ant. Marfort.\n\nMarget & Girard, Münsterberg 11. Agentur u. Commission. E. E. Girard-Laur u. Carl Schneider.\n\nMargreth-Geering Wwe. Elis., Part., 18 Byfangweg.\n\nMaring-Meyer Carl, Commis, 8 Eiseng.\n\n— -Rumpf Wwe. Emilie J., Partik., 1 Sattelg.\n\n— -Tschopp Ludw., Commis, 36 Heubg.\n\n— -Wierz Rud. L., Archit., 70 Freistr.\n\nMaring & Mertz, Weidengasse 5. Construction v. Maschinen. E. Ludw. Maring-Wirz u. Ign. Em. Mertz.\n\nMaritz-Schmid P. Claud., Landjäger, 4 Greifeng.\n\n— -Stöhr Augustin, Wirth, Holzhdl., 25 Bleicheweg.\n\nMark-Walz Xaver, Mechanikerges., 28 Birsigstr.\n\nMarkés-Jecklin C. Fr. Fl., Adjunkt der Zolldirect., 12 Byfangweg.\n\nMarkus Adolf, Ingenieur, 14 Missionsstr.\n\nMarosi-Bassy A.g., Chocoladenfabrikt., 32 Freistr.\n\nMarquart-Weber Domin., Arb. SCB, 2 Schnabelgässl.\n\nMarry-Stritt Fz. Jos., Kutscher, 26 Spitalstr.\n\nMarsch Henry, Commis, 15 Kohlenberg.\n\nMarthastift, Peterskirchplatz 1.\n\nMarthaler-Güttinger Frdr., Sattlermstr., 20 Barfüsserplatz.\n\nMarti Frdr., Lehrer am Waisenhaus, 7 Theodorskirchplatz.\n\n— -Gross M., Farbarb., 2 Amerbachstr.\n\n— -Hottinger Vict., Wirth, 1 Gerberg.\n\n— -Jac., Tagl., 63 Klingenthalstr.\n\n— -Marie Elisab., Fabrikarb., 12 Spalenberg.\n\n— -Reiniger Alois, Magazinknecht, 30 Rheing.\n"
  }
}