{
  "pdfPageNumber": 50,
  "surnameRange": [
    "Dietiker",
    "Dörflinger"
  ],
  "textColumns": {
    "Spalte01": "Dietiker\n---\n3\n\nDietiker-Gysin Joh., Posam., 73 Sperrstr.\n—Veiths.Rud., Droquist, 29 Schneiderg.\nDietler-Hierholzer Val., Schlosserges., 67\nFreistr.\nDietlin-Perrin Franz Jos., Ausläufer, 16\nHeuberg.\nDietmann Daniel, Handl., 37 Horburgstr.\n—Garten F., Maurererges., 1 Rappolsthof.\n—Günzer Dom., Angest. d. ELB, 8\nWeberg.\nDietrich Heinr., Taglöhner, 49 Nadelbg.\n—Huttenlocher Benj., Schlosserstr., 8 Leonhardsberg.\n—L. Josua, Bierbrauer, 31 Greifeng.\n—Keim Lud., Bierbrauer, 31 Greifeng.\n—Knecht Joh. Heinr., Schneiderg., 33\nHorburgstr.\n—Lydia, Näherin, 1 Peterskirchplatz.\n—Üehlinger Theoph. E., Kaminfeger,\n110 Hammerstr.\nDietsche-Hetzinger Paul, Bäckerges., 10\nSchafgässl.\n—Maisch Fridolin, Schuhmachermstr.,\n25 Unt. Heuberg.\n—Mauch C., Maurerg., 8 Breisacherstr.\nDietschy-Alioth Wilh., Bandfabrikant,\n9 Peterskirchpl.\n—(Brosi) Pet., Erdarbeiter, 36 Rebg.\n—Burckhardt Joh. Jakob, Bandfabrkt.,\n22 Johannvorst.\n—Faesch Joh., Rent., 33 Schützengr.\nDietschy-Faesch & Cie., Leonhardsgr. 10.\nWeine u. Spirituosen. E. Ed.\nFäsch-Kaufmann u. Herm. Häusser-\nPreiswerk.\n—Hermann Theodor, Tagl., 11 Hutg.\n—Lichtenhahn Jacob, Bandfabrik., 19\nJohannvorst.\n—Thalman Flor., Schneiderstr., 5\nSchnabelgässl.\nDietweiler Fridoline, Schneiderin, 17\nUnt. Rebg.\nDietz Carl, Zimmerges., 140 Bläsiringw.\n—Stänz Wwe. M., Tagl., 13 Malzg.\nDietze Carl, Zimmerges., 26 Spalenberg.\nDietziger-Gehring Albert, Bäckerges., 2\nAmerbachstr.\n—Stössel Joh. Ferd., Zimmerges., 129\nBläsiringweg.\nDieze-Diebold Conr., Handlanger, 37 Jo-\nhannvorst.",
    "Spalte02": "9 — Dörflinger\n\nDiggelmann-Uebelhardt Dav., Hafnerges., 13 Nauenstr.\n\nDilger-Eggmann C. Emil, Eidg. Zollbeamter, 68 Klingenthalstr.\n\n— -Sandhaas C., Commis, 21 Spalenvst.\n\nDill-Dürr J., Fuhrhalter, 161 Zürcherstr.\n\n— -Haas Math., Lehrer, 9 Clarastr.\n\n— -Tschann Wwe. Marg. C., Tagl., 4 Steinenthorstr.\n\n— -Utsinger Joh., Fbkarbtr., 18 Rümelinbachweg.\n\nDingeldein-Ramstein J. Adam, Zimmerg., 31 Horburgstr.\n\nDinkel-Brüderlin Franz, Maurerparl., 41 Aeschenger.\n\n— -Wunderli David, Kürschnerges., 8 Spalenberg.\n\nDinkelmann-Schmidt Gottl., Färberges., 84 Klingenthalstr.\n\nDippel-Desgouttes J. Friedr., Lederhdlg., 1 Köhlenberg.\n\nDippel & Cie., Kohlenbg.1. Häutehdlg. E. Jac.Friedr. Dippel u. Hermann Roth.\n\nDirhold Otto, Malermsr., 54 Clarastr.\n\nDiriwächter-(Hodel) J. G., Hausknecht, 10 Petersg.\n\n— -Suter J., Zimmerges., 37 Spalenberg.\n\nDischler-Güttinger Louis, Sattlermstr., 9 Bäumleing.\n\nDisler E., Telegraphist, 29 Steinenthorstr.\n\n— Joseph, Milchhdlr., 22 Steinenvorst.\n\n— -Peter Stephan, Milchhdlr., 8 Petersg.\n\nDittmer Eman., Part., 15 Spalenthorw.\n\n— -Meyer Wilh., Commis, 6 Nonnenweg.\n\n— Cath., Haushälterin i. d. kathol. Anstalt, 18 Lindenberg.\n\nDöbler-Alleon Mathilde L., Part., 11 Petersgr.\n\n— Gottfr., Commis SCB, 28 Freiestr.\n\n— Rudolf, Rent., 11 Langeg.\n\nDöbeli Emma, Postcommis, 8 Byfangw.\n\n— Wallburga, Taglöhnl, 18 Klingenthal.\n\n— -Weber Wwe. Bertha, Schneiderin, 39 Uteng.\n\nDöbelin Albertine u. Maria, Näherinnen, 13 Andreasp.\n\n— -Kiener Wwe. Rosalia, Schneiderin, 52 Herrengrabenweg.\n\nDörflinger Bernhardina, Fabrikarb., 47 Bläsiringweg.\n"
  }
}