{
  "pdfPageNumber": 216,
  "surnameRange": [
    "Schifferle",
    "Schlageter"
  ],
  "textColumns": {
    "Spalte01": "Schifferle — 20\n\nSchifferle-Banholzer Wwe. Maria, Tagl., 72 Rheing.\nSchiffmann-Mäder Barbara, Haushälterin, 105 Itelpfad.\nSchild-Basler Casp., Pfästerergeselle, 55 Klingenthalstr.\n-Sütterlin Johann, Pfästerermstr., 76 Isteinerstr.\nSchildknecht Ad., Ferger, 41 Rebg.\n-Näf Wwe. Maria, Haushält., 41 Rebg.\n-Vetter Wwe. Theresia, Haushälterin, 39 Johannvorst.\nSchill-Ernst Eduard, Wechselsensal, 28 Spalenthorweg.\n-Hess Salomea, Taglöhnl., 10 Peterskirchplatz.\n-Knechtli Verena, Fabrikarb., 10 Hutg.\n-Theresia, Näherin, 42 Farnsburgerstr.\nSchilling Ad., Commis, 7 Schützenmattstr.\n-Albert, Adjunct d. Schlachthausverw., 4 Elsässerstr.\n-Claus Ludwig, Tapezierermeister, 21 Heuberg.\n-Fischer Joh., Commis, 18 Nadelberg.\n-Hibbert Rud., Restaur., 1 Greifeng.\n-Jäcklin J. Rud., Hufschmied, 15 Spalenvorst.\nJac. Emil, Commis, 37 Feierabendstr.\n-Jenny Rudolf, Part., 37 Mittlerestr.\n-Johanna, Part., 1 Mühlenberg.\n-Kellermann Rud., Partic., 9 Johannvorst.\n-Lehmann Reinh., Zimmermstr., 153 Zürcherstr.\n-Louise, Part., 1 Mühlenberg.\n-Marg., Part., 53 Steinenvorst.\n-Marx, Landmann, 18 Riehenstr.\n-Müller Friedr., Zimmerges., 11 Lindenberg.\n-Rosenmund Alfred, Kaufmann, 32 Vogesenstr.\n-gen. Schluep Henriette, Näherin, 38 Heuberg.\n-Schmidt Friedr., Commis, 173 Albanringweg.\n-Stahl Robert, Commis, 146 Müllerweg.\n-Weitnauer Wwe. Marg. Elis., Part., 37 Feierabendstr.\n-Wilhelm Wwe. M. Ant., Partic., 3 Luftgässl.\nSchimpf-Holinger Wwe. Sophie, Fleckenreinigerin, 56 Spalenberg.",
    "Spalte02": "35 — Schlageter\n\nSchimpf-Kunzelmann Wwe. Ther., Abwartin, 3 Schlüsselberg.\n\nSchindelholz Elisabeth, Obsthdr., 12 Sattelg.\n\n— Kyburz Lorenz, Tagl., 13 Rheing.\n\nSchindler Arnold, Kunstmaler, 14 Missionsstr.\n\n— Leuzinger Otto, Lehrer, 37 Feierabendstr.\n\n— Rochat Arnold, Rentier, 14 Missionsstrasse.\n\n— Wilhelm, Commis, 25 Leimenstr.\n\nSchirach-Hofacker Wilh., Part., 20 Weiherweg.\n\nSchirmer-Maurer Jos., Tagl., 141 Holeestr.\n\nSchirrmeister-Kling Carl, Schreibmaterialhdlg., 71 Freiestr.\n\nSchlachter-Baur Pius, Mechanikerges., 40 Weberg.\n\n— Fäsch Jos. Franz, Commis, 7 hint. Spitalstr.\n\n— Franz, stud., 7 hint. Spitalg.\n\n— Frei Jos., Spähnhdlr., 27 Üteng.\n\n— Huber Fridol, Holzhdlr., 40 Maulbeerweg.\n\n— Juillerat Heinr., Kutscher, 56 Klingen-\n\nthalstr.\n\n— Leisin Jos., Packer, 28 Mattweg,\n\n— Müller Jos., Schmiediges., 57 Rheing.\n\n— Richterich Frau Marie, Fabrikarb.,\n\n18 Greifeng.\n\nSchlachthausverwaltung, Elsässerstr. 4.\n\nSchlack Anna Maria, Fabrikarb., 68 Klingen-\n\nthalstr.\n\nSchläpfer Carl, Kaufm., 20/22 Gerberg.\n\n— Keller Wittwe Sophie, Part., 81 Elsässerstr.\n\nSchlag-Jenny Alex. Arn., Dessinateur, 5 Streitg.\n\n— Sara, Zettlerin, 23 Holbeinstr.\n\n— Wagner H., Commis, 9 Bäumleing.\n\nSchlageter-Banwarth Fridol., Posam., 38 Maulbeerweg.\n\n— Bergmann Joseph, Fabrikmeister, 33 Greifeng.\n\n— Bieler Martin, Schneidermstr., 1 Im-\n\nborgässl.\n\n— Bollschweiler Rosine, Taglöhnerin,\n\n14 Gerbergässl.\n\n— Hug Wittwe Rosalia, Haushält., 14 Ulmenweg.\n\n— Hummel Ferd., Fabrikarb., 67 Amerbachstr.\n"
  }
}